{
  "generated_at": "2026-03-12T08:40:37",
  "status": "boert",
  "person": null,
  "times": null,
  "tauschpartner": [],
  "lotsen": [
    {
      "is_target": false,
      "pos": 1,
      "vorname": "Jan-Steffen",
      "nachname": "Glenewinkel",
      "arrow": null,
      "richtung": null,
      "verguetung": false,
      "zeit": "Thu Mar 12 07:46:59 CET 2026",
      "times": {
        "calc_div2": "Do09:10",
        "calc_div3": "Do09:00",
        "from_meldung": "Do08:55",
        "from_meldung_alt": "Do08:55"
      },
      "bemerkung": ""
    },
    {
      "is_target": false,
      "pos": 2,
      "vorname": "Volker",
      "nachname": "Nagel",
      "arrow": null,
      "richtung": null,
      "verguetung": false,
      "zeit": "Thu Mar 12 08:02:59 CET 2026",
      "times": {
        "calc_div2": "Do09:40",
        "calc_div3": "Do09:20",
        "from_meldung": "Do09:00",
        "from_meldung_alt": "Do09:00"
      },
      "bemerkung": ""
    },
    {
      "is_target": false,
      "pos": 3,
      "vorname": "Volker",
      "nachname": "Kahler",
      "arrow": null,
      "richtung": null,
      "verguetung": false,
      "zeit": "Thu Mar 12 08:03:59 CET 2026",
      "times": {
        "calc_div2": "Do10:10",
        "calc_div3": "Do09:40",
        "from_meldung": "Do09:20",
        "from_meldung_alt": "Do09:20"
      },
      "bemerkung": ""
    },
    {
      "is_target": false,
      "pos": 4,
      "vorname": "Hauke\r\n\t\t\t\t\t       \r\n\t\t\t\t\t\t\t\t\r\n\t  \t\t\t\t\t\t       (Schöppener, Matti)",
      "nachname": "Jeschek",
      "arrow": null,
      "richtung": null,
      "verguetung": false,
      "zeit": "Thu Mar 12 07:40:00 CET 2026",
      "times": {
        "calc_div2": "Do10:40",
        "calc_div3": "Do10:00",
        "from_meldung": "Do10:00",
        "from_meldung_alt": "Do10:00"
      },
      "bemerkung": ""
    },
    {
      "is_target": false,
      "pos": 5,
      "vorname": "Nik",
      "nachname": "Suermann",
      "arrow": null,
      "richtung": null,
      "verguetung": false,
      "zeit": "Thu Mar 12 07:46:00 CET 2026",
      "times": {
        "calc_div2": "Do11:10",
        "calc_div3": "Do10:20",
        "from_meldung": "Do10:00",
        "from_meldung_alt": "Do11:00"
      },
      "bemerkung": ""
    },
    {
      "is_target": false,
      "pos": 6,
      "vorname": "Andreas",
      "nachname": "Arlt",
      "arrow": null,
      "richtung": null,
      "verguetung": false,
      "zeit": "Thu Mar 12 08:00:00 CET 2026",
      "times": {
        "calc_div2": "Do11:40",
        "calc_div3": "Do10:40",
        "from_meldung": "Do11:00",
        "from_meldung_alt": "Do11:00"
      },
      "bemerkung": ""
    },
    {
      "is_target": false,
      "pos": 7,
      "vorname": "Eike",
      "nachname": "Matysik",
      "arrow": null,
      "richtung": null,
      "verguetung": false,
      "zeit": "Thu Mar 12 08:15:00 CET 2026",
      "times": {
        "calc_div2": "Do12:10",
        "calc_div3": "Do11:00",
        "from_meldung": "Do11:00",
        "from_meldung_alt": "Do11:40"
      },
      "bemerkung": ""
    },
    {
      "is_target": false,
      "pos": 8,
      "vorname": "Maximilian",
      "nachname": "Türk",
      "arrow": null,
      "richtung": null,
      "verguetung": false,
      "zeit": "Thu Mar 12 08:28:00 CET 2026",
      "times": {
        "calc_div2": "Do12:40",
        "calc_div3": "Do11:20",
        "from_meldung": "Do11:30",
        "from_meldung_alt": "Do12:00"
      },
      "bemerkung": ""
    },
    {
      "is_target": false,
      "pos": 9,
      "vorname": "Stephan",
      "nachname": "Thomaßen",
      "arrow": null,
      "richtung": null,
      "verguetung": false,
      "zeit": "Thu Mar 12 08:35:00 CET 2026",
      "times": {
        "calc_div2": "Do13:10",
        "calc_div3": "Do11:40",
        "from_meldung": "Do11:40",
        "from_meldung_alt": "Do12:00"
      },
      "bemerkung": ""
    },
    {
      "is_target": false,
      "pos": 10,
      "vorname": "Remo",
      "nachname": "Kordt",
      "arrow": null,
      "richtung": null,
      "verguetung": false,
      "zeit": "Thu Mar 12 08:36:00 CET 2026",
      "times": {
        "calc_div2": "Do13:40",
        "calc_div3": "Do12:00",
        "from_meldung": "Do12:00",
        "from_meldung_alt": "Do12:30"
      },
      "bemerkung": ""
    },
    {
      "is_target": false,
      "pos": 11,
      "vorname": "Helge",
      "nachname": "Rambadt",
      "arrow": null,
      "richtung": null,
      "verguetung": false,
      "zeit": "Wed Mar 11 01:01:00 CET 2026",
      "times": {
        "calc_div2": "Do14:10",
        "calc_div3": "Do12:20",
        "from_meldung": "Do12:00",
        "from_meldung_alt": "Do13:00"
      },
      "bemerkung": ""
    },
    {
      "is_target": false,
      "pos": 12,
      "vorname": "Mykola",
      "nachname": "Zozulya",
      "arrow": null,
      "richtung": null,
      "verguetung": false,
      "zeit": "Wed Mar 11 01:02:00 CET 2026",
      "times": {
        "calc_div2": "Do14:40",
        "calc_div3": "Do12:40",
        "from_meldung": "Do12:30",
        "from_meldung_alt": "Do13:30"
      },
      "bemerkung": ""
    },
    {
      "is_target": false,
      "pos": 13,
      "vorname": "Sven",
      "nachname": "Janson",
      "arrow": null,
      "richtung": null,
      "verguetung": false,
      "zeit": "Wed Mar 11 01:24:00 CET 2026",
      "times": {
        "calc_div2": "Do15:10",
        "calc_div3": "Do13:00",
        "from_meldung": "Do12:40",
        "from_meldung_alt": "Do13:40"
      },
      "bemerkung": ""
    },
    {
      "is_target": false,
      "pos": 14,
      "vorname": "Michael",
      "nachname": "Berkenheger",
      "arrow": null,
      "richtung": null,
      "verguetung": false,
      "zeit": "Wed Mar 11 02:58:00 CET 2026",
      "times": {
        "calc_div2": "Do15:40",
        "calc_div3": "Do13:20",
        "from_meldung": "Do12:40",
        "from_meldung_alt": "Do13:40"
      },
      "bemerkung": ""
    },
    {
      "is_target": false,
      "pos": 15,
      "vorname": "Jonas",
      "nachname": "Krämer",
      "arrow": null,
      "richtung": null,
      "verguetung": false,
      "zeit": "Wed Mar 11 03:11:00 CET 2026",
      "times": {
        "calc_div2": "Do16:10",
        "calc_div3": "Do13:40",
        "from_meldung": "Do13:00",
        "from_meldung_alt": "Do14:00"
      },
      "bemerkung": ""
    },
    {
      "is_target": false,
      "pos": 16,
      "vorname": "Frank",
      "nachname": "Staedler",
      "arrow": null,
      "richtung": null,
      "verguetung": false,
      "zeit": "Wed Mar 11 03:31:00 CET 2026",
      "times": {
        "calc_div2": "Do16:40",
        "calc_div3": "Do14:00",
        "from_meldung": "Do13:00",
        "from_meldung_alt": "Do14:15"
      },
      "bemerkung": ""
    },
    {
      "is_target": false,
      "pos": 17,
      "vorname": "Crischan",
      "nachname": "Czurda",
      "arrow": null,
      "richtung": null,
      "verguetung": false,
      "zeit": "Thu Mar 12 07:39:55 CET 2026",
      "times": {
        "calc_div2": "Do17:10",
        "calc_div3": "Do14:20",
        "from_meldung": "Do13:30",
        "from_meldung_alt": "Do14:20"
      },
      "bemerkung": ""
    },
    {
      "is_target": false,
      "pos": 18,
      "vorname": "Klaus Werner",
      "nachname": "Haala",
      "arrow": null,
      "richtung": null,
      "verguetung": false,
      "zeit": "Wed Mar 11 04:45:00 CET 2026",
      "times": {
        "calc_div2": "Do17:40",
        "calc_div3": "Do14:40",
        "from_meldung": "Do13:40",
        "from_meldung_alt": "Do16:35"
      },
      "bemerkung": ""
    },
    {
      "is_target": false,
      "pos": 19,
      "vorname": "Mathias",
      "nachname": "Krügel",
      "arrow": null,
      "richtung": null,
      "verguetung": false,
      "zeit": "Wed Mar 11 05:13:00 CET 2026",
      "times": {
        "calc_div2": "Do18:10",
        "calc_div3": "Do15:00",
        "from_meldung": "Do13:40",
        "from_meldung_alt": "Do16:40"
      },
      "bemerkung": ""
    },
    {
      "is_target": false,
      "pos": 20,
      "vorname": "Tom",
      "nachname": "Weise",
      "arrow": null,
      "richtung": null,
      "verguetung": false,
      "zeit": "Wed Mar 11 05:13:00 CET 2026",
      "times": {
        "calc_div2": "Do18:40",
        "calc_div3": "Do15:20",
        "from_meldung": "Do14:00",
        "from_meldung_alt": "Do17:00"
      },
      "bemerkung": ""
    },
    {
      "is_target": false,
      "pos": 21,
      "vorname": "Kai",
      "nachname": "Heyenga",
      "arrow": null,
      "richtung": null,
      "verguetung": false,
      "zeit": "Wed Mar 11 05:22:00 CET 2026",
      "times": {
        "calc_div2": "Do19:10",
        "calc_div3": "Do15:40",
        "from_meldung": "Do14:15",
        "from_meldung_alt": "Do17:00"
      },
      "bemerkung": ""
    },
    {
      "is_target": false,
      "pos": 22,
      "vorname": "Tom",
      "nachname": "Demant",
      "arrow": null,
      "richtung": null,
      "verguetung": false,
      "zeit": "Wed Mar 11 05:35:13 CET 2026",
      "times": {
        "calc_div2": "Do19:40",
        "calc_div3": "Do16:00",
        "from_meldung": "Do14:20",
        "from_meldung_alt": "Do17:00"
      },
      "bemerkung": ""
    },
    {
      "is_target": false,
      "pos": 23,
      "vorname": "Arne",
      "nachname": "Schulz",
      "arrow": null,
      "richtung": null,
      "verguetung": false,
      "zeit": "Wed Mar 11 06:12:00 CET 2026",
      "times": {
        "calc_div2": "Do20:10",
        "calc_div3": "Do16:20",
        "from_meldung": "Do15:40",
        "from_meldung_alt": "Do19:00"
      },
      "bemerkung": ""
    },
    {
      "is_target": false,
      "pos": 24,
      "vorname": "Henning",
      "nachname": "Blome",
      "arrow": "↓",
      "richtung": "↓",
      "verguetung": false,
      "zeit": "Wed Mar 11 07:28:00 CET 2026",
      "times": {
        "calc_div2": "Do20:40",
        "calc_div3": "Do16:40",
        "from_meldung": "Do16:00",
        "from_meldung_alt": "Do19:00"
      },
      "bemerkung": ""
    },
    {
      "is_target": false,
      "pos": 25,
      "vorname": "René",
      "nachname": "Winkler",
      "arrow": null,
      "richtung": null,
      "verguetung": false,
      "zeit": "Wed Mar 11 07:34:00 CET 2026",
      "times": {
        "calc_div2": "Do21:10",
        "calc_div3": "Do17:00",
        "from_meldung": "Do16:00",
        "from_meldung_alt": "Do19:00"
      },
      "bemerkung": ""
    },
    {
      "is_target": false,
      "pos": 26,
      "vorname": "Steffen",
      "nachname": "Zimmermann",
      "arrow": "↓",
      "richtung": "↓",
      "verguetung": false,
      "zeit": "Wed Mar 11 07:36:00 CET 2026",
      "times": {
        "calc_div2": "Do21:40",
        "calc_div3": "Do17:20",
        "from_meldung": "Do16:35",
        "from_meldung_alt": "Do19:00"
      },
      "bemerkung": ""
    },
    {
      "is_target": false,
      "pos": 27,
      "vorname": "Tim",
      "nachname": "Woitanowski",
      "arrow": null,
      "richtung": null,
      "verguetung": false,
      "zeit": "Wed Mar 11 07:36:00 CET 2026",
      "times": {
        "calc_div2": "Do22:10",
        "calc_div3": "Do17:40",
        "from_meldung": "Do16:40",
        "from_meldung_alt": "Do19:00"
      },
      "bemerkung": ""
    },
    {
      "is_target": false,
      "pos": 28,
      "vorname": "Malte",
      "nachname": "Krause",
      "arrow": "↑$$",
      "richtung": "↑",
      "verguetung": true,
      "zeit": "Wed Mar 11 10:20:00 CET 2026",
      "times": {
        "calc_div2": "Do22:40",
        "calc_div3": "Do18:00",
        "from_meldung": "Do17:00",
        "from_meldung_alt": "Do21:00"
      },
      "bemerkung": ""
    },
    {
      "is_target": false,
      "pos": 29,
      "vorname": "Gregor",
      "nachname": "Kubica",
      "arrow": "↓",
      "richtung": "↓",
      "verguetung": false,
      "zeit": "Wed Mar 11 11:44:00 CET 2026",
      "times": {
        "calc_div2": "Do23:10",
        "calc_div3": "Do18:20",
        "from_meldung": "Do17:00",
        "from_meldung_alt": "Do22:00"
      },
      "bemerkung": ""
    },
    {
      "is_target": false,
      "pos": 30,
      "vorname": "Denny",
      "nachname": "Pankonin",
      "arrow": null,
      "richtung": null,
      "verguetung": false,
      "zeit": "Wed Mar 11 11:54:00 CET 2026",
      "times": {
        "calc_div2": "Do23:40",
        "calc_div3": "Do18:40",
        "from_meldung": "Do17:00",
        "from_meldung_alt": "Do23:00"
      },
      "bemerkung": ""
    },
    {
      "is_target": false,
      "pos": 31,
      "vorname": "Yannick",
      "nachname": "Petersen",
      "arrow": null,
      "richtung": null,
      "verguetung": false,
      "zeit": "Wed Mar 11 11:55:00 CET 2026",
      "times": {
        "calc_div2": "Fr00:10",
        "calc_div3": "Do19:00",
        "from_meldung": "Do18:00",
        "from_meldung_alt": "Do23:00"
      },
      "bemerkung": ""
    },
    {
      "is_target": false,
      "pos": 32,
      "vorname": "Mark",
      "nachname": "Wald",
      "arrow": null,
      "richtung": null,
      "verguetung": false,
      "zeit": "Wed Mar 11 12:30:52 CET 2026",
      "times": {
        "calc_div2": "Fr00:40",
        "calc_div3": "Do19:20",
        "from_meldung": "Do18:00",
        "from_meldung_alt": "Fr00:00"
      },
      "bemerkung": ""
    },
    {
      "is_target": false,
      "pos": 33,
      "vorname": "Jan",
      "nachname": "Hilpert",
      "arrow": null,
      "richtung": null,
      "verguetung": false,
      "zeit": "Wed Mar 11 12:39:00 CET 2026",
      "times": {
        "calc_div2": "Fr01:10",
        "calc_div3": "Do19:40",
        "from_meldung": "Do18:00",
        "from_meldung_alt": "Fr00:00"
      },
      "bemerkung": ""
    },
    {
      "is_target": false,
      "pos": 34,
      "vorname": "Curt",
      "nachname": "Börnsen",
      "arrow": null,
      "richtung": null,
      "verguetung": false,
      "zeit": "Wed Mar 11 15:25:25 CET 2026",
      "times": {
        "calc_div2": "Fr01:40",
        "calc_div3": "Do20:00",
        "from_meldung": "Do18:00",
        "from_meldung_alt": "Fr00:00"
      },
      "bemerkung": ""
    },
    {
      "is_target": false,
      "pos": 35,
      "vorname": "Gerhard",
      "nachname": "Alt",
      "arrow": null,
      "richtung": null,
      "verguetung": false,
      "zeit": "Wed Mar 11 16:20:00 CET 2026",
      "times": {
        "calc_div2": "Fr02:10",
        "calc_div3": "Do20:20",
        "from_meldung": "Do19:00",
        "from_meldung_alt": "Fr00:00"
      },
      "bemerkung": ""
    },
    {
      "is_target": false,
      "pos": 36,
      "vorname": "Alexander",
      "nachname": "Hren",
      "arrow": null,
      "richtung": null,
      "verguetung": false,
      "zeit": "Wed Mar 11 16:20:00 CET 2026",
      "times": {
        "calc_div2": "Fr02:40",
        "calc_div3": "Do20:40",
        "from_meldung": "Do19:00",
        "from_meldung_alt": "Fr02:00"
      },
      "bemerkung": ""
    },
    {
      "is_target": false,
      "pos": 37,
      "vorname": "Thomas",
      "nachname": "Dietrich",
      "arrow": null,
      "richtung": null,
      "verguetung": false,
      "zeit": "Wed Mar 11 16:40:00 CET 2026",
      "times": {
        "calc_div2": "Fr03:10",
        "calc_div3": "Do21:00",
        "from_meldung": "Do19:00",
        "from_meldung_alt": "Fr03:00"
      },
      "bemerkung": ""
    },
    {
      "is_target": false,
      "pos": 38,
      "vorname": "Jens-Peter",
      "nachname": "Töpfer",
      "arrow": null,
      "richtung": null,
      "verguetung": false,
      "zeit": "Wed Mar 11 16:41:50 CET 2026",
      "times": {
        "calc_div2": "Fr03:40",
        "calc_div3": "Do21:20",
        "from_meldung": "Do19:00",
        "from_meldung_alt": "Fr04:00"
      },
      "bemerkung": ""
    },
    {
      "is_target": false,
      "pos": 39,
      "vorname": "Sebastian",
      "nachname": "Lüttge",
      "arrow": null,
      "richtung": null,
      "verguetung": false,
      "zeit": "Wed Mar 11 17:13:00 CET 2026",
      "times": {
        "calc_div2": "Fr04:10",
        "calc_div3": "Do21:40",
        "from_meldung": "Do19:00",
        "from_meldung_alt": "Fr05:00"
      },
      "bemerkung": ""
    },
    {
      "is_target": false,
      "pos": 40,
      "vorname": "Olaf",
      "nachname": "Köhler",
      "arrow": null,
      "richtung": null,
      "verguetung": false,
      "zeit": "Wed Mar 11 17:19:00 CET 2026",
      "times": {
        "calc_div2": "Fr04:40",
        "calc_div3": "Do22:00",
        "from_meldung": "Do20:00",
        "from_meldung_alt": "Fr05:20"
      },
      "bemerkung": ""
    },
    {
      "is_target": false,
      "pos": 41,
      "vorname": "Marko",
      "nachname": "Purwin",
      "arrow": null,
      "richtung": null,
      "verguetung": false,
      "zeit": "Wed Mar 11 17:20:00 CET 2026",
      "times": {
        "calc_div2": "Fr05:10",
        "calc_div3": "Do22:20",
        "from_meldung": "Do21:00",
        "from_meldung_alt": "Fr06:30"
      },
      "bemerkung": ""
    },
    {
      "is_target": false,
      "pos": 42,
      "vorname": "Oliver\r\n\t\t\t\t\t       \r\n\t\t\t\t\t\t\t\t\r\n\t  \t\t\t\t\t\t       (Reuter, Sophia)",
      "nachname": "Schran",
      "arrow": "↓",
      "richtung": "↓",
      "verguetung": false,
      "zeit": "Wed Mar 11 18:24:00 CET 2026",
      "times": {
        "calc_div2": "Fr05:40",
        "calc_div3": "Do22:40",
        "from_meldung": "Do21:00",
        "from_meldung_alt": "Fr07:00"
      },
      "bemerkung": ""
    },
    {
      "is_target": false,
      "pos": 43,
      "vorname": "Ingmar\r\n\t\t\t\t\t       \r\n\t\t\t\t\t\t\t\t\r\n\t  \t\t\t\t\t\t       (Schnieders, Ken)",
      "nachname": "Richter",
      "arrow": null,
      "richtung": null,
      "verguetung": false,
      "zeit": "Wed Mar 11 18:26:00 CET 2026",
      "times": {
        "calc_div2": "Fr06:10",
        "calc_div3": "Do23:00",
        "from_meldung": "Do22:00",
        "from_meldung_alt": "Fr07:00"
      },
      "bemerkung": ""
    },
    {
      "is_target": false,
      "pos": 44,
      "vorname": "Jörn",
      "nachname": "Lielienthal",
      "arrow": "↓$$",
      "richtung": "↓",
      "verguetung": true,
      "zeit": "Wed Mar 11 18:33:00 CET 2026",
      "times": {
        "calc_div2": "Fr06:40",
        "calc_div3": "Do23:20",
        "from_meldung": "Do22:00",
        "from_meldung_alt": "Fr07:00"
      },
      "bemerkung": "max. Tk 56"
    },
    {
      "is_target": false,
      "pos": 45,
      "vorname": "Peter",
      "nachname": "Hüpers",
      "arrow": null,
      "richtung": null,
      "verguetung": false,
      "zeit": "Wed Mar 11 18:34:00 CET 2026",
      "times": {
        "calc_div2": "Fr07:10",
        "calc_div3": "Do23:40",
        "from_meldung": "Do23:00",
        "from_meldung_alt": "Fr07:20"
      },
      "bemerkung": ""
    },
    {
      "is_target": false,
      "pos": 46,
      "vorname": "Peter",
      "nachname": "Vogel",
      "arrow": null,
      "richtung": null,
      "verguetung": false,
      "zeit": "Wed Mar 11 18:55:00 CET 2026",
      "times": {
        "calc_div2": "Fr07:40",
        "calc_div3": "Fr00:00",
        "from_meldung": "Do23:00",
        "from_meldung_alt": "Fr08:00"
      },
      "bemerkung": ""
    },
    {
      "is_target": false,
      "pos": 47,
      "vorname": "Janning",
      "nachname": "Otten",
      "arrow": null,
      "richtung": null,
      "verguetung": false,
      "zeit": "Wed Mar 11 19:32:00 CET 2026",
      "times": {
        "calc_div2": "Fr08:10",
        "calc_div3": "Fr00:20",
        "from_meldung": "Do23:00",
        "from_meldung_alt": null
      },
      "bemerkung": ""
    },
    {
      "is_target": false,
      "pos": 48,
      "vorname": "Claas",
      "nachname": "Cramer",
      "arrow": "↑$$",
      "richtung": "↑",
      "verguetung": true,
      "zeit": "Wed Mar 11 19:42:00 CET 2026",
      "times": {
        "calc_div2": "Fr08:40",
        "calc_div3": "Fr00:40",
        "from_meldung": "Do23:00",
        "from_meldung_alt": null
      },
      "bemerkung": "max tkt 24"
    },
    {
      "is_target": false,
      "pos": 49,
      "vorname": "Dennis",
      "nachname": "Heyenga",
      "arrow": "↓",
      "richtung": "↓",
      "verguetung": false,
      "zeit": "Wed Mar 11 20:10:00 CET 2026",
      "times": {
        "calc_div2": "Fr09:10",
        "calc_div3": "Fr01:00",
        "from_meldung": "Do23:00",
        "from_meldung_alt": null
      },
      "bemerkung": ""
    },
    {
      "is_target": false,
      "pos": 50,
      "vorname": "Jan",
      "nachname": "Stürenburg",
      "arrow": "↓",
      "richtung": "↓",
      "verguetung": false,
      "zeit": "Wed Mar 11 20:30:00 CET 2026",
      "times": {
        "calc_div2": "Fr09:40",
        "calc_div3": "Fr01:20",
        "from_meldung": "Do23:00",
        "from_meldung_alt": null
      },
      "bemerkung": ""
    },
    {
      "is_target": false,
      "pos": 51,
      "vorname": "Tomas",
      "nachname": "Witte",
      "arrow": null,
      "richtung": null,
      "verguetung": false,
      "zeit": "Wed Mar 11 21:20:00 CET 2026",
      "times": {
        "calc_div2": "Fr10:10",
        "calc_div3": "Fr01:40",
        "from_meldung": "Fr00:00",
        "from_meldung_alt": null
      },
      "bemerkung": ""
    },
    {
      "is_target": false,
      "pos": 52,
      "vorname": "Olaf",
      "nachname": "Tontarra",
      "arrow": null,
      "richtung": null,
      "verguetung": false,
      "zeit": "Wed Mar 11 21:31:00 CET 2026",
      "times": {
        "calc_div2": "Fr10:40",
        "calc_div3": "Fr02:00",
        "from_meldung": "Fr00:00",
        "from_meldung_alt": null
      },
      "bemerkung": ""
    },
    {
      "is_target": false,
      "pos": 53,
      "vorname": "Christian",
      "nachname": "Wille",
      "arrow": null,
      "richtung": null,
      "verguetung": false,
      "zeit": "Wed Mar 11 22:02:00 CET 2026",
      "times": {
        "calc_div2": "Fr11:10",
        "calc_div3": "Fr02:20",
        "from_meldung": "Fr00:00",
        "from_meldung_alt": null
      },
      "bemerkung": ""
    },
    {
      "is_target": false,
      "pos": 54,
      "vorname": "Hüseyin",
      "nachname": "Ünsal",
      "arrow": null,
      "richtung": null,
      "verguetung": false,
      "zeit": "Wed Mar 11 23:38:00 CET 2026",
      "times": {
        "calc_div2": "Fr11:40",
        "calc_div3": "Fr02:40",
        "from_meldung": "Fr00:00",
        "from_meldung_alt": null
      },
      "bemerkung": ""
    },
    {
      "is_target": false,
      "pos": 55,
      "vorname": "Stephan",
      "nachname": "Wulff",
      "arrow": null,
      "richtung": null,
      "verguetung": false,
      "zeit": "Wed Mar 11 23:46:00 CET 2026",
      "times": {
        "calc_div2": "Fr12:10",
        "calc_div3": "Fr03:00",
        "from_meldung": "Fr02:00",
        "from_meldung_alt": null
      },
      "bemerkung": ""
    },
    {
      "is_target": false,
      "pos": 56,
      "vorname": "Hark",
      "nachname": "Borggräfe",
      "arrow": null,
      "richtung": null,
      "verguetung": false,
      "zeit": "Thu Mar 12 00:07:00 CET 2026",
      "times": {
        "calc_div2": "Fr12:40",
        "calc_div3": "Fr03:20",
        "from_meldung": "Fr03:00",
        "from_meldung_alt": null
      },
      "bemerkung": ""
    },
    {
      "is_target": false,
      "pos": 57,
      "vorname": "Knut Paul",
      "nachname": "Klüver",
      "arrow": null,
      "richtung": null,
      "verguetung": false,
      "zeit": "Thu Mar 12 00:25:00 CET 2026",
      "times": {
        "calc_div2": "Fr13:10",
        "calc_div3": "Fr03:40",
        "from_meldung": "Fr03:00",
        "from_meldung_alt": null
      },
      "bemerkung": ""
    },
    {
      "is_target": false,
      "pos": 58,
      "vorname": "Niels",
      "nachname": "Münker",
      "arrow": null,
      "richtung": null,
      "verguetung": false,
      "zeit": "Thu Mar 12 01:15:00 CET 2026",
      "times": {
        "calc_div2": "Fr13:40",
        "calc_div3": "Fr04:00",
        "from_meldung": "Fr04:00",
        "from_meldung_alt": null
      },
      "bemerkung": ""
    },
    {
      "is_target": false,
      "pos": 59,
      "vorname": "Gunnar",
      "nachname": "Thomsen",
      "arrow": null,
      "richtung": null,
      "verguetung": false,
      "zeit": "Thu Mar 12 01:29:00 CET 2026",
      "times": {
        "calc_div2": "Fr14:10",
        "calc_div3": "Fr04:20",
        "from_meldung": "Fr04:00",
        "from_meldung_alt": null
      },
      "bemerkung": ""
    },
    {
      "is_target": false,
      "pos": 60,
      "vorname": "Alexander",
      "nachname": "Stoislow",
      "arrow": null,
      "richtung": null,
      "verguetung": false,
      "zeit": "Thu Mar 12 02:00:00 CET 2026",
      "times": {
        "calc_div2": "Fr14:40",
        "calc_div3": "Fr04:40",
        "from_meldung": "Fr05:00",
        "from_meldung_alt": null
      },
      "bemerkung": ""
    },
    {
      "is_target": false,
      "pos": 61,
      "vorname": "Thomas",
      "nachname": "Schmidt",
      "arrow": null,
      "richtung": null,
      "verguetung": false,
      "zeit": "Thu Mar 12 02:16:00 CET 2026",
      "times": {
        "calc_div2": "Fr15:10",
        "calc_div3": "Fr05:00",
        "from_meldung": "Fr05:20",
        "from_meldung_alt": null
      },
      "bemerkung": ""
    },
    {
      "is_target": false,
      "pos": 62,
      "vorname": "Jens",
      "nachname": "Röhl",
      "arrow": null,
      "richtung": null,
      "verguetung": false,
      "zeit": "Thu Mar 12 02:16:00 CET 2026",
      "times": {
        "calc_div2": "Fr15:40",
        "calc_div3": "Fr05:20",
        "from_meldung": "Fr06:00",
        "from_meldung_alt": null
      },
      "bemerkung": ""
    },
    {
      "is_target": false,
      "pos": 63,
      "vorname": "Hannes",
      "nachname": "Rink",
      "arrow": null,
      "richtung": null,
      "verguetung": false,
      "zeit": "Thu Mar 12 04:30:00 CET 2026",
      "times": {
        "calc_div2": "Fr16:10",
        "calc_div3": "Fr05:40",
        "from_meldung": "Fr06:00",
        "from_meldung_alt": null
      },
      "bemerkung": ""
    },
    {
      "is_target": false,
      "pos": 64,
      "vorname": "Christian",
      "nachname": "Lehwald",
      "arrow": null,
      "richtung": null,
      "verguetung": false,
      "zeit": "Thu Mar 12 04:31:00 CET 2026",
      "times": {
        "calc_div2": "Fr16:40",
        "calc_div3": "Fr06:00",
        "from_meldung": "Fr06:30",
        "from_meldung_alt": null
      },
      "bemerkung": ""
    },
    {
      "is_target": false,
      "pos": 65,
      "vorname": "Johannes",
      "nachname": "Biedermann",
      "arrow": null,
      "richtung": null,
      "verguetung": false,
      "zeit": "Thu Mar 12 05:15:00 CET 2026",
      "times": {
        "calc_div2": "Fr17:10",
        "calc_div3": "Fr06:20",
        "from_meldung": "Fr07:00",
        "from_meldung_alt": null
      },
      "bemerkung": ""
    },
    {
      "is_target": false,
      "pos": 66,
      "vorname": "Marius",
      "nachname": "Schüler",
      "arrow": null,
      "richtung": null,
      "verguetung": false,
      "zeit": "Thu Mar 12 05:24:00 CET 2026",
      "times": {
        "calc_div2": "Fr17:40",
        "calc_div3": "Fr06:40",
        "from_meldung": "Fr07:00",
        "from_meldung_alt": null
      },
      "bemerkung": ""
    },
    {
      "is_target": false,
      "pos": 67,
      "vorname": "Alexander",
      "nachname": "Migge",
      "arrow": null,
      "richtung": null,
      "verguetung": false,
      "zeit": "Thu Mar 12 07:16:00 CET 2026",
      "times": {
        "calc_div2": "Fr18:10",
        "calc_div3": "Fr07:00",
        "from_meldung": "Fr07:00",
        "from_meldung_alt": null
      },
      "bemerkung": ""
    },
    {
      "is_target": false,
      "pos": 68,
      "vorname": "Jürgen",
      "nachname": "Marth",
      "arrow": null,
      "richtung": null,
      "verguetung": false,
      "zeit": "Thu Mar 12 07:52:36 CET 2026",
      "times": {
        "calc_div2": "Fr18:40",
        "calc_div3": "Fr07:20",
        "from_meldung": "Fr07:00",
        "from_meldung_alt": null
      },
      "bemerkung": ""
    },
    {
      "is_target": false,
      "pos": 69,
      "vorname": "Thomas",
      "nachname": "Skairies",
      "arrow": null,
      "richtung": null,
      "verguetung": false,
      "zeit": "Thu Mar 12 08:01:00 CET 2026",
      "times": {
        "calc_div2": "Fr19:10",
        "calc_div3": "Fr07:40",
        "from_meldung": "Fr07:20",
        "from_meldung_alt": null
      },
      "bemerkung": ""
    }
  ]
}