{
  "generated_at": "2026-05-08T19:51:43",
  "target": {
    "slug": "konietzka_stefan",
    "display_name": "konietzka, stefan",
    "nachname": "konietzka",
    "vorname": "stefan",
    "watch_user_key": "ubgbxnv8qjmbu5mjaoksxahte2725p"
  },
  "state": {
    "kind": "gesamtboert",
    "source": "Gesamtboert.json",
    "pos": "34",
    "takt": "12,0"
  },
  "action_card": {
    "title": "konietzka, stefan",
    "subtitle": "Gesamtbört",
    "state_kind": "gesamtboert",
    "state_label": "Gesamtbört",
    "q_gruppe": "5",
    "pos": "34",
    "takt": "12,0",
    "workstart_label": "Start: 2026-05-09 08:00",
    "badges": [
      "Q 5",
      "Pos 34"
    ],
    "lines": [
      "Takt: 12,0",
      "Start: 2026-05-09 08:00"
    ]
  },
  "q_gruppe": "5",
  "workstart": {
    "ts_calc": "2026-05-08 19:50",
    "pos": 34,
    "from_meldung": "2026-05-09 08:00",
    "from_meldung_alt": "2026-05-09 19:00",
    "calc_div2": "2026-05-09 12:50",
    "calc_div3": "2026-05-09 07:10",
    "real_start": null
  },
  "workstart_meta": {
    "file": "workstart_history_konietzka_stefan.json",
    "exists": true,
    "generated_at": "2026-05-08T19:50:58",
    "entry_count": 1434
  },
  "boert": {
    "entry": {
      "pos": "34",
      "takt": "12,0",
      "nachname": "Konietzka",
      "vorname": "Stefan",
      "q_gruppe": "5",
      "was": "ZUG",
      "zeit": "Fri May 08 07:13:00 CEST 2026",
      "bemerkung": "",
      "arrow": null
    },
    "entry_count": 1
  },
  "seelotsen": {
    "entries": [],
    "entry_count": 0
  },
  "related_ships": [],
  "person_files": {
    "status": {
      "file": "konietzka_stefan_status.json",
      "exists": true,
      "generated_at": "2026-05-08 19:50"
    },
    "pos": {
      "file": "konietzka_stefan_pos.json",
      "exists": true
    },
    "short": {
      "file": "konietzka_stefan_short.json",
      "exists": true
    },
    "long": {
      "file": "konietzka_stefan_long.json",
      "exists": true
    },
    "workstart_history_json": {
      "file": "workstart_history_konietzka_stefan.json",
      "exists": true,
      "generated_at": "2026-05-08T19:50:58"
    },
    "workstart_history_jsonl": {
      "file": "workstart_history_konietzka_stefan.jsonl",
      "exists": true
    }
  },
  "snapshots": {
    "status": {
      "generated_at": "2026-05-08 19:50",
      "nachname": "konietzka",
      "vorname": "stefan",
      "status": {
        "willkommen": "Willkommen Stefan Konietzka",
        "zuletzt": "08.05.-07:13 ZUG",
        "naechster_urlaub": "18.05.2026"
      }
    },
    "pos": {
      "pos": 34
    },
    "short": {
      "key": "konietzka_stefan",
      "status": "boert",
      "short": "Gesamtbört – Pos 34\n08:00\n19:00\nPos/2: 12:50 (+1d)\nPos/3: 07:10 (+1d)\nAkt.: 19:51"
    },
    "long": {
      "key": "konietzka_stefan",
      "status": "boert",
      "long": "Gesamtbört\n----------\nKiel 52 / RÜB 3\n\n 8  | Jeske   | Fr22:00 / Fr22:50 / Fr22:30~Fr23:50\n      | ↓   | –                    \n 11 | Zimmermann | Fr22:53 / Fr23:00 / Fr23:30~Sa01:20\n      | ↓   | –                    \n 14 | Steinbach | Fr23:00 / Sa00:00 / Sa00:30~Sa02:50\n      | ↓   | –                    \n 15 | Stürenburg | Fr23:00 / Sa01:03 / Sa00:50~Sa03:20\n      | ↓   | –                    \n 27 | Skairies | Sa04:00 / Sa11:00 / Sa04:50~Sa09:20\n      | ↓   | –                    \n 31 | Heeren  | Sa05:00 / Sa15:00 / Sa06:10~Sa11:20\n      | ↓   | –                    \n▶34 | Konietzka | 08:00 / 19:00 / 07:10 (+1d)~12:50 (+1d)\n      | –   | –                    \n 38 | Lielienthal | Sa11:00 / Sa08:30~Sa14:50\n      | ↑$$ | 𝗠𝗮𝘅 takt 5           \n\nAkt.: 19:51"
    }
  },
  "source_meta": {
    "gesamtboert": {
      "file": "Gesamtboert.json",
      "exists": true,
      "generated_at": "2026-05-08 19:50",
      "count": 65
    },
    "seelotsen": {
      "file": "Seelotsen.json",
      "exists": true,
      "generated_at": "2026-05-08 19:50",
      "count": 24
    },
    "meldungen_kiel": {
      "file": "Meldungen_Kiel.json",
      "exists": true,
      "generated_at": "2026-05-08 19:50",
      "count": 52
    },
    "meldungen_ruesterbergen": {
      "file": "Meldungen_Ruesterbergen.json",
      "exists": true,
      "generated_at": "2026-05-08 19:50",
      "count": 3
    },
    "q_gruppen": {
      "file": "q_gruppen_lotsen.json",
      "exists": true,
      "generated_at": "2026-05-08T19:51:27",
      "count": 150
    },
    "schiffe_merged": {
      "file": "schiffe_merged.json",
      "exists": true,
      "generated_at": "2026-05-08T19:51:27",
      "count": 69
    },
    "workstart_history_json": {
      "file": "workstart_history_konietzka_stefan.json",
      "exists": true,
      "generated_at": "2026-05-08T19:50:58",
      "count": 1434
    }
  }
}