{
  "generated_at": "2026-05-03T18:39:06",
  "status": "boert",
  "person": {
    "vorname": "christian",
    "nachname": "lehwald",
    "pos": 40,
    "takt": "82,0",
    "times": {
      "calc_div2": "Mo14:39",
      "calc_div2_dt": "2026-05-04 14:39",
      "calc_div3": "Mo07:59",
      "calc_div3_dt": "2026-05-04 07:59",
      "from_meldung": "Mo10:00",
      "from_meldung_dt": "2026-05-04 10:00",
      "from_meldung_alt": "Mo15:20",
      "from_meldung_alt_dt": "2026-05-04 15:20"
    },
    "bemerkung": ""
  },
  "times": {
    "calc_div2": "Mo14:39",
    "calc_div2_dt": "2026-05-04 14:39",
    "calc_div3": "Mo07:59",
    "calc_div3_dt": "2026-05-04 07:59",
    "from_meldung": "Mo10:00",
    "from_meldung_dt": "2026-05-04 10:00",
    "from_meldung_alt": "Mo15:20",
    "from_meldung_alt_dt": "2026-05-04 15:20"
  },
  "tauschpartner": [
    {
      "is_target": false,
      "pos": 17,
      "takt": "59,0",
      "vorname": "Curt",
      "nachname": "Börnsen",
      "arrow": "↓",
      "richtung": "↓",
      "verguetung": false,
      "zeit": "Sat May 02 17:21:00 CEST 2026",
      "times": {
        "calc_div2": "Mo03:09",
        "calc_div2_dt": "2026-05-04 03:09",
        "calc_div3": "Mo00:19",
        "calc_div3_dt": "2026-05-04 00:19",
        "from_meldung": "So23:40",
        "from_meldung_dt": "2026-05-03 23:40",
        "from_meldung_alt": "Mo01:30",
        "from_meldung_alt_dt": "2026-05-04 01:30"
      },
      "bemerkung": ""
    },
    {
      "is_target": false,
      "pos": 31,
      "takt": "73,0",
      "vorname": "Marko",
      "nachname": "Purwin",
      "arrow": "↓",
      "richtung": "↓",
      "verguetung": false,
      "zeit": "Sun May 03 01:30:03 CEST 2026",
      "times": {
        "calc_div2": "Mo10:09",
        "calc_div2_dt": "2026-05-04 10:09",
        "calc_div3": "Mo04:59",
        "calc_div3_dt": "2026-05-04 04:59",
        "from_meldung": "Mo06:30",
        "from_meldung_dt": "2026-05-04 06:30",
        "from_meldung_alt": "Mo07:50",
        "from_meldung_alt_dt": "2026-05-04 07:50"
      },
      "bemerkung": ""
    },
    {
      "is_target": false,
      "pos": 39,
      "takt": "81,0",
      "vorname": "Peter",
      "nachname": "Hahn",
      "arrow": "↓",
      "richtung": "↓",
      "verguetung": false,
      "zeit": "Sun May 03 04:28:45 CEST 2026",
      "times": {
        "calc_div2": "Mo14:09",
        "calc_div2_dt": "2026-05-04 14:09",
        "calc_div3": "Mo07:39",
        "calc_div3_dt": "2026-05-04 07:39",
        "from_meldung": "Mo09:00",
        "from_meldung_dt": "2026-05-04 09:00",
        "from_meldung_alt": "Mo15:00",
        "from_meldung_alt_dt": "2026-05-04 15:00"
      },
      "bemerkung": ""
    },
    {
      "is_target": false,
      "pos": 43,
      "takt": "85,0",
      "vorname": "Micha",
      "nachname": "Steffens",
      "arrow": "↑$$",
      "richtung": "↑",
      "verguetung": true,
      "zeit": "Sun May 03 05:45:00 CEST 2026",
      "times": {
        "calc_div2": "Mo16:09",
        "calc_div2_dt": "2026-05-04 16:09",
        "calc_div3": "Mo08:59",
        "calc_div3_dt": "2026-05-04 08:59",
        "from_meldung": "Mo12:00",
        "from_meldung_dt": "2026-05-04 12:00",
        "from_meldung_alt": null,
        "from_meldung_alt_dt": null
      },
      "bemerkung": ""
    },
    {
      "is_target": false,
      "pos": 45,
      "takt": "87,0",
      "vorname": "Franck",
      "nachname": "Escher",
      "arrow": "↑$$",
      "richtung": "↑",
      "verguetung": true,
      "zeit": "Sun May 03 08:04:00 CEST 2026",
      "times": {
        "calc_div2": "Mo17:09",
        "calc_div2_dt": "2026-05-04 17:09",
        "calc_div3": "Mo09:39",
        "calc_div3_dt": "2026-05-04 09:39",
        "from_meldung": "Mo13:30",
        "from_meldung_dt": "2026-05-04 13:30",
        "from_meldung_alt": null,
        "from_meldung_alt_dt": null
      },
      "bemerkung": "tk55 max"
    },
    {
      "is_target": false,
      "pos": 54,
      "takt": "96,0",
      "vorname": "Caspar-Maria",
      "nachname": "Krüger",
      "arrow": "↑$$",
      "richtung": "↑",
      "verguetung": true,
      "zeit": "Sun May 03 12:30:00 CEST 2026",
      "times": {
        "calc_div2": "Mo21:39",
        "calc_div2_dt": "2026-05-04 21:39",
        "calc_div3": "Mo12:39",
        "calc_div3_dt": "2026-05-04 12:39",
        "from_meldung": "Mo17:00",
        "from_meldung_dt": "2026-05-04 17:00",
        "from_meldung_alt": null,
        "from_meldung_alt_dt": null
      },
      "bemerkung": ""
    },
    {
      "is_target": false,
      "pos": 59,
      "takt": "1,0",
      "vorname": "Christoph",
      "nachname": "Malik",
      "arrow": "↑$$",
      "richtung": "↑",
      "verguetung": true,
      "zeit": "Sun May 03 15:19:00 CEST 2026",
      "times": {
        "calc_div2": "Di00:09",
        "calc_div2_dt": "2026-05-05 00:09",
        "calc_div3": "Mo14:19",
        "calc_div3_dt": "2026-05-04 14:19",
        "from_meldung": null,
        "from_meldung_dt": null,
        "from_meldung_alt": null,
        "from_meldung_alt_dt": null
      },
      "bemerkung": "max.10.Wache"
    }
  ],
  "lotsen": [
    {
      "is_target": false,
      "pos": 1,
      "takt": "42,0",
      "vorname": "Martin",
      "nachname": "Wachsmuth",
      "arrow": null,
      "richtung": null,
      "verguetung": false,
      "zeit": "Sun May 03 15:44:00 CEST 2026",
      "times": {
        "calc_div2": "So19:09",
        "calc_div2_dt": "2026-05-03 19:09",
        "calc_div3": "So18:59",
        "calc_div3_dt": "2026-05-03 18:59",
        "from_meldung": "So19:00",
        "from_meldung_dt": "2026-05-03 19:00",
        "from_meldung_alt": "So19:00",
        "from_meldung_alt_dt": "2026-05-03 19:00"
      },
      "bemerkung": ""
    },
    {
      "is_target": false,
      "pos": 2,
      "takt": "45,0",
      "vorname": "Julian",
      "nachname": "Plaisant",
      "arrow": null,
      "richtung": null,
      "verguetung": false,
      "zeit": "Sun May 03 16:20:00 CEST 2026",
      "times": {
        "calc_div2": "So19:39",
        "calc_div2_dt": "2026-05-03 19:39",
        "calc_div3": "So19:19",
        "calc_div3_dt": "2026-05-03 19:19",
        "from_meldung": "So19:10",
        "from_meldung_dt": "2026-05-03 19:10",
        "from_meldung_alt": "So19:30",
        "from_meldung_alt_dt": "2026-05-03 19:30"
      },
      "bemerkung": ""
    },
    {
      "is_target": false,
      "pos": 3,
      "takt": "46,0",
      "vorname": "Jan",
      "nachname": "Kurfeld",
      "arrow": null,
      "richtung": null,
      "verguetung": false,
      "zeit": "Sun May 03 16:20:00 CEST 2026",
      "times": {
        "calc_div2": "So20:09",
        "calc_div2_dt": "2026-05-03 20:09",
        "calc_div3": "So19:39",
        "calc_div3_dt": "2026-05-03 19:39",
        "from_meldung": "So19:30",
        "from_meldung_dt": "2026-05-03 19:30",
        "from_meldung_alt": "So19:35",
        "from_meldung_alt_dt": "2026-05-03 19:35"
      },
      "bemerkung": ""
    },
    {
      "is_target": false,
      "pos": 4,
      "takt": "47,0",
      "vorname": "Niels",
      "nachname": "Münker",
      "arrow": null,
      "richtung": null,
      "verguetung": false,
      "zeit": "Sun May 03 16:20:00 CEST 2026",
      "times": {
        "calc_div2": "So20:39",
        "calc_div2_dt": "2026-05-03 20:39",
        "calc_div3": "So19:59",
        "calc_div3_dt": "2026-05-03 19:59",
        "from_meldung": "So19:35",
        "from_meldung_dt": "2026-05-03 19:35",
        "from_meldung_alt": "So19:40",
        "from_meldung_alt_dt": "2026-05-03 19:40"
      },
      "bemerkung": ""
    },
    {
      "is_target": false,
      "pos": 5,
      "takt": "48,0",
      "vorname": "Tom",
      "nachname": "Demant",
      "arrow": null,
      "richtung": null,
      "verguetung": false,
      "zeit": "Sun May 03 16:20:00 CEST 2026",
      "times": {
        "calc_div2": "So21:09",
        "calc_div2_dt": "2026-05-03 21:09",
        "calc_div3": "So20:19",
        "calc_div3_dt": "2026-05-03 20:19",
        "from_meldung": "So19:40",
        "from_meldung_dt": "2026-05-03 19:40",
        "from_meldung_alt": "So19:45",
        "from_meldung_alt_dt": "2026-05-03 19:45"
      },
      "bemerkung": ""
    },
    {
      "is_target": false,
      "pos": 6,
      "takt": "49,0",
      "vorname": "Arne",
      "nachname": "Schulz",
      "arrow": null,
      "richtung": null,
      "verguetung": false,
      "zeit": "Sun May 03 16:30:00 CEST 2026",
      "times": {
        "calc_div2": "So21:39",
        "calc_div2_dt": "2026-05-03 21:39",
        "calc_div3": "So20:39",
        "calc_div3_dt": "2026-05-03 20:39",
        "from_meldung": "So19:45",
        "from_meldung_dt": "2026-05-03 19:45",
        "from_meldung_alt": "So20:10",
        "from_meldung_alt_dt": "2026-05-03 20:10"
      },
      "bemerkung": ""
    },
    {
      "is_target": false,
      "pos": 7,
      "takt": "50,0",
      "vorname": "Artur",
      "nachname": "Skawianczyk",
      "arrow": null,
      "richtung": null,
      "verguetung": false,
      "zeit": "Sun May 03 16:30:00 CEST 2026",
      "times": {
        "calc_div2": "So22:09",
        "calc_div2_dt": "2026-05-03 22:09",
        "calc_div3": "So20:59",
        "calc_div3_dt": "2026-05-03 20:59",
        "from_meldung": "So20:00",
        "from_meldung_dt": "2026-05-03 20:00",
        "from_meldung_alt": "So21:00",
        "from_meldung_alt_dt": "2026-05-03 21:00"
      },
      "bemerkung": ""
    },
    {
      "is_target": false,
      "pos": 8,
      "takt": "51,0",
      "vorname": "Yannick",
      "nachname": "Petersen",
      "arrow": null,
      "richtung": null,
      "verguetung": false,
      "zeit": "Sun May 03 17:08:00 CEST 2026",
      "times": {
        "calc_div2": "So22:39",
        "calc_div2_dt": "2026-05-03 22:39",
        "calc_div3": "So21:19",
        "calc_div3_dt": "2026-05-03 21:19",
        "from_meldung": "So20:10",
        "from_meldung_dt": "2026-05-03 20:10",
        "from_meldung_alt": "So21:25",
        "from_meldung_alt_dt": "2026-05-03 21:25"
      },
      "bemerkung": "Zehnte durchgeben"
    },
    {
      "is_target": false,
      "pos": 9,
      "takt": "52,0",
      "vorname": "Lars",
      "nachname": "Doering",
      "arrow": null,
      "richtung": null,
      "verguetung": false,
      "zeit": "Sun May 03 17:32:00 CEST 2026",
      "times": {
        "calc_div2": "So23:09",
        "calc_div2_dt": "2026-05-03 23:09",
        "calc_div3": "So21:39",
        "calc_div3_dt": "2026-05-03 21:39",
        "from_meldung": "So21:00",
        "from_meldung_dt": "2026-05-03 21:00",
        "from_meldung_alt": "So21:30",
        "from_meldung_alt_dt": "2026-05-03 21:30"
      },
      "bemerkung": ""
    },
    {
      "is_target": false,
      "pos": 10,
      "takt": "52,1",
      "vorname": "Olaf",
      "nachname": "Köhler",
      "arrow": null,
      "richtung": null,
      "verguetung": false,
      "zeit": "Sun May 03 18:35:00 CEST 2026",
      "times": {
        "calc_div2": "So23:39",
        "calc_div2_dt": "2026-05-03 23:39",
        "calc_div3": "So21:59",
        "calc_div3_dt": "2026-05-03 21:59",
        "from_meldung": "So21:25",
        "from_meldung_dt": "2026-05-03 21:25",
        "from_meldung_alt": "So21:35",
        "from_meldung_alt_dt": "2026-05-03 21:35"
      },
      "bemerkung": ""
    },
    {
      "is_target": false,
      "pos": 11,
      "takt": "53,0",
      "vorname": "Tom\r\n\t\t\t\t\t       \r\n\t\t\t\t\t\t\t\t\r\n\t  \t\t\t\t\t\t       (Schöppener, Matti)",
      "nachname": "Weise",
      "arrow": null,
      "richtung": null,
      "verguetung": false,
      "zeit": "Sat May 02 16:33:00 CEST 2026",
      "times": {
        "calc_div2": "Mo00:09",
        "calc_div2_dt": "2026-05-04 00:09",
        "calc_div3": "So22:19",
        "calc_div3_dt": "2026-05-03 22:19",
        "from_meldung": "So21:30",
        "from_meldung_dt": "2026-05-03 21:30",
        "from_meldung_alt": "So21:38",
        "from_meldung_alt_dt": "2026-05-03 21:38"
      },
      "bemerkung": ""
    },
    {
      "is_target": false,
      "pos": 12,
      "takt": "54,0",
      "vorname": "Stefan",
      "nachname": "Bruhn",
      "arrow": null,
      "richtung": null,
      "verguetung": false,
      "zeit": "Sat May 02 16:45:00 CEST 2026",
      "times": {
        "calc_div2": "Mo00:39",
        "calc_div2_dt": "2026-05-04 00:39",
        "calc_div3": "So22:39",
        "calc_div3_dt": "2026-05-03 22:39",
        "from_meldung": "So21:35",
        "from_meldung_dt": "2026-05-03 21:35",
        "from_meldung_alt": "So23:30",
        "from_meldung_alt_dt": "2026-05-03 23:30"
      },
      "bemerkung": ""
    },
    {
      "is_target": false,
      "pos": 13,
      "takt": "55,0",
      "vorname": "Hinnerk",
      "nachname": "Hansen",
      "arrow": null,
      "richtung": null,
      "verguetung": false,
      "zeit": "Sat May 02 16:45:00 CEST 2026",
      "times": {
        "calc_div2": "Mo01:09",
        "calc_div2_dt": "2026-05-04 01:09",
        "calc_div3": "So22:59",
        "calc_div3_dt": "2026-05-03 22:59",
        "from_meldung": "So21:38",
        "from_meldung_dt": "2026-05-03 21:38",
        "from_meldung_alt": "So23:30",
        "from_meldung_alt_dt": "2026-05-03 23:30"
      },
      "bemerkung": ""
    },
    {
      "is_target": false,
      "pos": 14,
      "takt": "56,0",
      "vorname": "Justus",
      "nachname": "Heyder",
      "arrow": null,
      "richtung": null,
      "verguetung": false,
      "zeit": "Sat May 02 17:00:00 CEST 2026",
      "times": {
        "calc_div2": "Mo01:39",
        "calc_div2_dt": "2026-05-04 01:39",
        "calc_div3": "So23:19",
        "calc_div3_dt": "2026-05-03 23:19",
        "from_meldung": "So22:30",
        "from_meldung_dt": "2026-05-03 22:30",
        "from_meldung_alt": "So23:40",
        "from_meldung_alt_dt": "2026-05-03 23:40"
      },
      "bemerkung": ""
    },
    {
      "is_target": false,
      "pos": 15,
      "takt": "57,0",
      "vorname": "Philipp",
      "nachname": "Crotogino",
      "arrow": null,
      "richtung": null,
      "verguetung": false,
      "zeit": "Sat May 02 17:08:00 CEST 2026",
      "times": {
        "calc_div2": "Mo02:09",
        "calc_div2_dt": "2026-05-04 02:09",
        "calc_div3": "So23:39",
        "calc_div3_dt": "2026-05-03 23:39",
        "from_meldung": "So23:30",
        "from_meldung_dt": "2026-05-03 23:30",
        "from_meldung_alt": "Mo00:30",
        "from_meldung_alt_dt": "2026-05-04 00:30"
      },
      "bemerkung": ""
    },
    {
      "is_target": false,
      "pos": 16,
      "takt": "58,0",
      "vorname": "Gregor",
      "nachname": "Meise",
      "arrow": null,
      "richtung": null,
      "verguetung": false,
      "zeit": "Sat May 02 17:15:00 CEST 2026",
      "times": {
        "calc_div2": "Mo02:39",
        "calc_div2_dt": "2026-05-04 02:39",
        "calc_div3": "So23:59",
        "calc_div3_dt": "2026-05-03 23:59",
        "from_meldung": "So23:30",
        "from_meldung_dt": "2026-05-03 23:30",
        "from_meldung_alt": "Mo01:30",
        "from_meldung_alt_dt": "2026-05-04 01:30"
      },
      "bemerkung": ""
    },
    {
      "is_target": false,
      "pos": 17,
      "takt": "59,0",
      "vorname": "Curt",
      "nachname": "Börnsen",
      "arrow": "↓",
      "richtung": "↓",
      "verguetung": false,
      "zeit": "Sat May 02 17:21:00 CEST 2026",
      "times": {
        "calc_div2": "Mo03:09",
        "calc_div2_dt": "2026-05-04 03:09",
        "calc_div3": "Mo00:19",
        "calc_div3_dt": "2026-05-04 00:19",
        "from_meldung": "So23:40",
        "from_meldung_dt": "2026-05-03 23:40",
        "from_meldung_alt": "Mo01:30",
        "from_meldung_alt_dt": "2026-05-04 01:30"
      },
      "bemerkung": ""
    },
    {
      "is_target": false,
      "pos": 18,
      "takt": "60,0",
      "vorname": "Michael",
      "nachname": "Krebs",
      "arrow": null,
      "richtung": null,
      "verguetung": false,
      "zeit": "Sat May 02 19:15:00 CEST 2026",
      "times": {
        "calc_div2": "Mo03:39",
        "calc_div2_dt": "2026-05-04 03:39",
        "calc_div3": "Mo00:39",
        "calc_div3_dt": "2026-05-04 00:39",
        "from_meldung": "Mo00:30",
        "from_meldung_dt": "2026-05-04 00:30",
        "from_meldung_alt": "Mo01:45",
        "from_meldung_alt_dt": "2026-05-04 01:45"
      },
      "bemerkung": ""
    },
    {
      "is_target": false,
      "pos": 19,
      "takt": "61,0",
      "vorname": "Marius Paul",
      "nachname": "Hewig",
      "arrow": null,
      "richtung": null,
      "verguetung": false,
      "zeit": "Sat May 02 19:29:00 CEST 2026",
      "times": {
        "calc_div2": "Mo04:09",
        "calc_div2_dt": "2026-05-04 04:09",
        "calc_div3": "Mo00:59",
        "calc_div3_dt": "2026-05-04 00:59",
        "from_meldung": "Mo01:00",
        "from_meldung_dt": "2026-05-04 01:00",
        "from_meldung_alt": "Mo02:00",
        "from_meldung_alt_dt": "2026-05-04 02:00"
      },
      "bemerkung": ""
    },
    {
      "is_target": false,
      "pos": 20,
      "takt": "62,0",
      "vorname": "Jörn",
      "nachname": "Lielienthal",
      "arrow": null,
      "richtung": null,
      "verguetung": false,
      "zeit": "Sat May 02 20:30:00 CEST 2026",
      "times": {
        "calc_div2": "Mo04:39",
        "calc_div2_dt": "2026-05-04 04:39",
        "calc_div3": "Mo01:19",
        "calc_div3_dt": "2026-05-04 01:19",
        "from_meldung": "Mo01:30",
        "from_meldung_dt": "2026-05-04 01:30",
        "from_meldung_alt": "Mo02:05",
        "from_meldung_alt_dt": "2026-05-04 02:05"
      },
      "bemerkung": ""
    },
    {
      "is_target": false,
      "pos": 21,
      "takt": "63,0",
      "vorname": "Hauke",
      "nachname": "Jeschek",
      "arrow": null,
      "richtung": null,
      "verguetung": false,
      "zeit": "Sat May 02 20:50:00 CEST 2026",
      "times": {
        "calc_div2": "Mo05:09",
        "calc_div2_dt": "2026-05-04 05:09",
        "calc_div3": "Mo01:39",
        "calc_div3_dt": "2026-05-04 01:39",
        "from_meldung": "Mo01:30",
        "from_meldung_dt": "2026-05-04 01:30",
        "from_meldung_alt": "Mo02:08",
        "from_meldung_alt_dt": "2026-05-04 02:08"
      },
      "bemerkung": ""
    },
    {
      "is_target": false,
      "pos": 22,
      "takt": "64,0",
      "vorname": "Dolf",
      "nachname": "Jenckel",
      "arrow": null,
      "richtung": null,
      "verguetung": false,
      "zeit": "Sat May 02 20:58:00 CEST 2026",
      "times": {
        "calc_div2": "Mo05:39",
        "calc_div2_dt": "2026-05-04 05:39",
        "calc_div3": "Mo01:59",
        "calc_div3_dt": "2026-05-04 01:59",
        "from_meldung": "Mo01:45",
        "from_meldung_dt": "2026-05-04 01:45",
        "from_meldung_alt": "Mo03:00",
        "from_meldung_alt_dt": "2026-05-04 03:00"
      },
      "bemerkung": "max.takt.52"
    },
    {
      "is_target": false,
      "pos": 23,
      "takt": "65,0",
      "vorname": "Torben",
      "nachname": "Keyser",
      "arrow": null,
      "richtung": null,
      "verguetung": false,
      "zeit": "Sat May 02 21:25:00 CEST 2026",
      "times": {
        "calc_div2": "Mo06:09",
        "calc_div2_dt": "2026-05-04 06:09",
        "calc_div3": "Mo02:19",
        "calc_div3_dt": "2026-05-04 02:19",
        "from_meldung": "Mo02:00",
        "from_meldung_dt": "2026-05-04 02:00",
        "from_meldung_alt": "Mo04:00",
        "from_meldung_alt_dt": "2026-05-04 04:00"
      },
      "bemerkung": ""
    },
    {
      "is_target": false,
      "pos": 24,
      "takt": "66,0",
      "vorname": "Gerd",
      "nachname": "Pitschmann",
      "arrow": null,
      "richtung": null,
      "verguetung": false,
      "zeit": "Sat May 02 22:37:00 CEST 2026",
      "times": {
        "calc_div2": "Mo06:39",
        "calc_div2_dt": "2026-05-04 06:39",
        "calc_div3": "Mo02:39",
        "calc_div3_dt": "2026-05-04 02:39",
        "from_meldung": "Mo02:05",
        "from_meldung_dt": "2026-05-04 02:05",
        "from_meldung_alt": "Mo04:00",
        "from_meldung_alt_dt": "2026-05-04 04:00"
      },
      "bemerkung": ""
    },
    {
      "is_target": false,
      "pos": 25,
      "takt": "67,0",
      "vorname": "Nils",
      "nachname": "Föhring",
      "arrow": null,
      "richtung": null,
      "verguetung": false,
      "zeit": "Sat May 02 22:37:32 CEST 2026",
      "times": {
        "calc_div2": "Mo07:09",
        "calc_div2_dt": "2026-05-04 07:09",
        "calc_div3": "Mo02:59",
        "calc_div3_dt": "2026-05-04 02:59",
        "from_meldung": "Mo02:08",
        "from_meldung_dt": "2026-05-04 02:08",
        "from_meldung_alt": "Mo06:00",
        "from_meldung_alt_dt": "2026-05-04 06:00"
      },
      "bemerkung": ""
    },
    {
      "is_target": false,
      "pos": 26,
      "takt": "68,0",
      "vorname": "Remo",
      "nachname": "Kordt",
      "arrow": null,
      "richtung": null,
      "verguetung": false,
      "zeit": "Sat May 02 22:37:39 CEST 2026",
      "times": {
        "calc_div2": "Mo07:39",
        "calc_div2_dt": "2026-05-04 07:39",
        "calc_div3": "Mo03:19",
        "calc_div3_dt": "2026-05-04 03:19",
        "from_meldung": "Mo03:00",
        "from_meldung_dt": "2026-05-04 03:00",
        "from_meldung_alt": "Mo06:30",
        "from_meldung_alt_dt": "2026-05-04 06:30"
      },
      "bemerkung": ""
    },
    {
      "is_target": false,
      "pos": 27,
      "takt": "69,0",
      "vorname": "Henning",
      "nachname": "Kaschke",
      "arrow": null,
      "richtung": null,
      "verguetung": false,
      "zeit": "Sat May 02 22:42:03 CEST 2026",
      "times": {
        "calc_div2": "Mo08:09",
        "calc_div2_dt": "2026-05-04 08:09",
        "calc_div3": "Mo03:39",
        "calc_div3_dt": "2026-05-04 03:39",
        "from_meldung": "Mo04:00",
        "from_meldung_dt": "2026-05-04 04:00",
        "from_meldung_alt": "Mo06:30",
        "from_meldung_alt_dt": "2026-05-04 06:30"
      },
      "bemerkung": ""
    },
    {
      "is_target": false,
      "pos": 28,
      "takt": "70,0",
      "vorname": "Christian",
      "nachname": "Wille",
      "arrow": null,
      "richtung": null,
      "verguetung": false,
      "zeit": "Sat May 02 22:52:19 CEST 2026",
      "times": {
        "calc_div2": "Mo08:39",
        "calc_div2_dt": "2026-05-04 08:39",
        "calc_div3": "Mo03:59",
        "calc_div3_dt": "2026-05-04 03:59",
        "from_meldung": "Mo04:00",
        "from_meldung_dt": "2026-05-04 04:00",
        "from_meldung_alt": "Mo06:45",
        "from_meldung_alt_dt": "2026-05-04 06:45"
      },
      "bemerkung": ""
    },
    {
      "is_target": false,
      "pos": 29,
      "takt": "71,0",
      "vorname": "Jan",
      "nachname": "Christiansen",
      "arrow": null,
      "richtung": null,
      "verguetung": false,
      "zeit": "Sun May 03 00:32:49 CEST 2026",
      "times": {
        "calc_div2": "Mo09:09",
        "calc_div2_dt": "2026-05-04 09:09",
        "calc_div3": "Mo04:19",
        "calc_div3_dt": "2026-05-04 04:19",
        "from_meldung": "Mo06:00",
        "from_meldung_dt": "2026-05-04 06:00",
        "from_meldung_alt": "Mo07:00",
        "from_meldung_alt_dt": "2026-05-04 07:00"
      },
      "bemerkung": ""
    },
    {
      "is_target": false,
      "pos": 30,
      "takt": "72,0",
      "vorname": "Johannes",
      "nachname": "Röhrs",
      "arrow": null,
      "richtung": null,
      "verguetung": false,
      "zeit": "Sun May 03 01:13:00 CEST 2026",
      "times": {
        "calc_div2": "Mo09:39",
        "calc_div2_dt": "2026-05-04 09:39",
        "calc_div3": "Mo04:39",
        "calc_div3_dt": "2026-05-04 04:39",
        "from_meldung": "Mo06:00",
        "from_meldung_dt": "2026-05-04 06:00",
        "from_meldung_alt": "Mo07:30",
        "from_meldung_alt_dt": "2026-05-04 07:30"
      },
      "bemerkung": ""
    },
    {
      "is_target": false,
      "pos": 31,
      "takt": "73,0",
      "vorname": "Marko",
      "nachname": "Purwin",
      "arrow": "↓",
      "richtung": "↓",
      "verguetung": false,
      "zeit": "Sun May 03 01:30:03 CEST 2026",
      "times": {
        "calc_div2": "Mo10:09",
        "calc_div2_dt": "2026-05-04 10:09",
        "calc_div3": "Mo04:59",
        "calc_div3_dt": "2026-05-04 04:59",
        "from_meldung": "Mo06:30",
        "from_meldung_dt": "2026-05-04 06:30",
        "from_meldung_alt": "Mo07:50",
        "from_meldung_alt_dt": "2026-05-04 07:50"
      },
      "bemerkung": ""
    },
    {
      "is_target": false,
      "pos": 32,
      "takt": "74,0",
      "vorname": "Kevin",
      "nachname": "Koslik",
      "arrow": null,
      "richtung": null,
      "verguetung": false,
      "zeit": "Sun May 03 01:49:19 CEST 2026",
      "times": {
        "calc_div2": "Mo10:39",
        "calc_div2_dt": "2026-05-04 10:39",
        "calc_div3": "Mo05:19",
        "calc_div3_dt": "2026-05-04 05:19",
        "from_meldung": "Mo06:30",
        "from_meldung_dt": "2026-05-04 06:30",
        "from_meldung_alt": "Mo10:00",
        "from_meldung_alt_dt": "2026-05-04 10:00"
      },
      "bemerkung": ""
    },
    {
      "is_target": false,
      "pos": 33,
      "takt": "75,0",
      "vorname": "Klaus Werner",
      "nachname": "Haala",
      "arrow": null,
      "richtung": null,
      "verguetung": false,
      "zeit": "Sun May 03 03:15:16 CEST 2026",
      "times": {
        "calc_div2": "Mo11:09",
        "calc_div2_dt": "2026-05-04 11:09",
        "calc_div3": "Mo05:39",
        "calc_div3_dt": "2026-05-04 05:39",
        "from_meldung": "Mo06:30",
        "from_meldung_dt": "2026-05-04 06:30",
        "from_meldung_alt": "Mo11:00",
        "from_meldung_alt_dt": "2026-05-04 11:00"
      },
      "bemerkung": ""
    },
    {
      "is_target": false,
      "pos": 34,
      "takt": "76,0",
      "vorname": "Oleif Johann",
      "nachname": "Böttger",
      "arrow": null,
      "richtung": null,
      "verguetung": false,
      "zeit": "Sun May 03 03:15:23 CEST 2026",
      "times": {
        "calc_div2": "Mo11:39",
        "calc_div2_dt": "2026-05-04 11:39",
        "calc_div3": "Mo05:59",
        "calc_div3_dt": "2026-05-04 05:59",
        "from_meldung": "Mo06:45",
        "from_meldung_dt": "2026-05-04 06:45",
        "from_meldung_alt": "Mo12:00",
        "from_meldung_alt_dt": "2026-05-04 12:00"
      },
      "bemerkung": ""
    },
    {
      "is_target": false,
      "pos": 35,
      "takt": "77,0",
      "vorname": "Christoph",
      "nachname": "Bodmann",
      "arrow": null,
      "richtung": null,
      "verguetung": false,
      "zeit": "Sun May 03 03:18:28 CEST 2026",
      "times": {
        "calc_div2": "Mo12:09",
        "calc_div2_dt": "2026-05-04 12:09",
        "calc_div3": "Mo06:19",
        "calc_div3_dt": "2026-05-04 06:19",
        "from_meldung": "Mo07:00",
        "from_meldung_dt": "2026-05-04 07:00",
        "from_meldung_alt": "Mo13:00",
        "from_meldung_alt_dt": "2026-05-04 13:00"
      },
      "bemerkung": ""
    },
    {
      "is_target": false,
      "pos": 36,
      "takt": "78,0",
      "vorname": "Michael",
      "nachname": "Arndt",
      "arrow": null,
      "richtung": null,
      "verguetung": false,
      "zeit": "Sun May 03 03:18:32 CEST 2026",
      "times": {
        "calc_div2": "Mo12:39",
        "calc_div2_dt": "2026-05-04 12:39",
        "calc_div3": "Mo06:39",
        "calc_div3_dt": "2026-05-04 06:39",
        "from_meldung": "Mo07:30",
        "from_meldung_dt": "2026-05-04 07:30",
        "from_meldung_alt": "Mo13:30",
        "from_meldung_alt_dt": "2026-05-04 13:30"
      },
      "bemerkung": ""
    },
    {
      "is_target": false,
      "pos": 37,
      "takt": "79,0",
      "vorname": "Jonas",
      "nachname": "Krämer",
      "arrow": null,
      "richtung": null,
      "verguetung": false,
      "zeit": "Sun May 03 03:18:38 CEST 2026",
      "times": {
        "calc_div2": "Mo13:09",
        "calc_div2_dt": "2026-05-04 13:09",
        "calc_div3": "Mo06:59",
        "calc_div3_dt": "2026-05-04 06:59",
        "from_meldung": "Mo07:50",
        "from_meldung_dt": "2026-05-04 07:50",
        "from_meldung_alt": "Mo15:00",
        "from_meldung_alt_dt": "2026-05-04 15:00"
      },
      "bemerkung": ""
    },
    {
      "is_target": false,
      "pos": 38,
      "takt": "80,0",
      "vorname": "Helge",
      "nachname": "Rambadt",
      "arrow": null,
      "richtung": null,
      "verguetung": false,
      "zeit": "Sun May 03 04:28:45 CEST 2026",
      "times": {
        "calc_div2": "Mo13:39",
        "calc_div2_dt": "2026-05-04 13:39",
        "calc_div3": "Mo07:19",
        "calc_div3_dt": "2026-05-04 07:19",
        "from_meldung": "Mo08:35",
        "from_meldung_dt": "2026-05-04 08:35",
        "from_meldung_alt": "Mo15:00",
        "from_meldung_alt_dt": "2026-05-04 15:00"
      },
      "bemerkung": ""
    },
    {
      "is_target": false,
      "pos": 39,
      "takt": "81,0",
      "vorname": "Peter",
      "nachname": "Hahn",
      "arrow": "↓",
      "richtung": "↓",
      "verguetung": false,
      "zeit": "Sun May 03 04:28:45 CEST 2026",
      "times": {
        "calc_div2": "Mo14:09",
        "calc_div2_dt": "2026-05-04 14:09",
        "calc_div3": "Mo07:39",
        "calc_div3_dt": "2026-05-04 07:39",
        "from_meldung": "Mo09:00",
        "from_meldung_dt": "2026-05-04 09:00",
        "from_meldung_alt": "Mo15:00",
        "from_meldung_alt_dt": "2026-05-04 15:00"
      },
      "bemerkung": ""
    },
    {
      "is_target": true,
      "pos": 40,
      "takt": "82,0",
      "vorname": "Christian",
      "nachname": "Lehwald",
      "arrow": "↓",
      "richtung": "↓",
      "verguetung": false,
      "zeit": "Sun May 03 04:30:53 CEST 2026",
      "times": {
        "calc_div2": "Mo14:39",
        "calc_div2_dt": "2026-05-04 14:39",
        "calc_div3": "Mo07:59",
        "calc_div3_dt": "2026-05-04 07:59",
        "from_meldung": "Mo10:00",
        "from_meldung_dt": "2026-05-04 10:00",
        "from_meldung_alt": "Mo15:20",
        "from_meldung_alt_dt": "2026-05-04 15:20"
      },
      "bemerkung": ""
    },
    {
      "is_target": false,
      "pos": 41,
      "takt": "83,0",
      "vorname": "Roman",
      "nachname": "Spiller",
      "arrow": "↓",
      "richtung": "↓",
      "verguetung": false,
      "zeit": "Sun May 03 05:08:36 CEST 2026",
      "times": {
        "calc_div2": "Mo15:09",
        "calc_div2_dt": "2026-05-04 15:09",
        "calc_div3": "Mo08:19",
        "calc_div3_dt": "2026-05-04 08:19",
        "from_meldung": "Mo11:00",
        "from_meldung_dt": "2026-05-04 11:00",
        "from_meldung_alt": "Mo17:00",
        "from_meldung_alt_dt": "2026-05-04 17:00"
      },
      "bemerkung": ""
    },
    {
      "is_target": false,
      "pos": 42,
      "takt": "84,0",
      "vorname": "Knut Paul",
      "nachname": "Klüver",
      "arrow": null,
      "richtung": null,
      "verguetung": false,
      "zeit": "Sun May 03 05:33:00 CEST 2026",
      "times": {
        "calc_div2": "Mo15:39",
        "calc_div2_dt": "2026-05-04 15:39",
        "calc_div3": "Mo08:39",
        "calc_div3_dt": "2026-05-04 08:39",
        "from_meldung": "Mo12:00",
        "from_meldung_dt": "2026-05-04 12:00",
        "from_meldung_alt": "Mo18:00",
        "from_meldung_alt_dt": "2026-05-04 18:00"
      },
      "bemerkung": ""
    },
    {
      "is_target": false,
      "pos": 43,
      "takt": "85,0",
      "vorname": "Micha",
      "nachname": "Steffens",
      "arrow": "↑$$",
      "richtung": "↑",
      "verguetung": true,
      "zeit": "Sun May 03 05:45:00 CEST 2026",
      "times": {
        "calc_div2": "Mo16:09",
        "calc_div2_dt": "2026-05-04 16:09",
        "calc_div3": "Mo08:59",
        "calc_div3_dt": "2026-05-04 08:59",
        "from_meldung": "Mo12:00",
        "from_meldung_dt": "2026-05-04 12:00",
        "from_meldung_alt": null,
        "from_meldung_alt_dt": null
      },
      "bemerkung": ""
    },
    {
      "is_target": false,
      "pos": 44,
      "takt": "86,0",
      "vorname": "Helge",
      "nachname": "Buch",
      "arrow": null,
      "richtung": null,
      "verguetung": false,
      "zeit": "Sun May 03 06:31:00 CEST 2026",
      "times": {
        "calc_div2": "Mo16:39",
        "calc_div2_dt": "2026-05-04 16:39",
        "calc_div3": "Mo09:19",
        "calc_div3_dt": "2026-05-04 09:19",
        "from_meldung": "Mo13:00",
        "from_meldung_dt": "2026-05-04 13:00",
        "from_meldung_alt": null,
        "from_meldung_alt_dt": null
      },
      "bemerkung": ""
    },
    {
      "is_target": false,
      "pos": 45,
      "takt": "87,0",
      "vorname": "Franck",
      "nachname": "Escher",
      "arrow": "↑$$",
      "richtung": "↑",
      "verguetung": true,
      "zeit": "Sun May 03 08:04:00 CEST 2026",
      "times": {
        "calc_div2": "Mo17:09",
        "calc_div2_dt": "2026-05-04 17:09",
        "calc_div3": "Mo09:39",
        "calc_div3_dt": "2026-05-04 09:39",
        "from_meldung": "Mo13:30",
        "from_meldung_dt": "2026-05-04 13:30",
        "from_meldung_alt": null,
        "from_meldung_alt_dt": null
      },
      "bemerkung": "tk55 max"
    },
    {
      "is_target": false,
      "pos": 46,
      "takt": "88,0",
      "vorname": "Jürgen",
      "nachname": "Marth",
      "arrow": null,
      "richtung": null,
      "verguetung": false,
      "zeit": "Sun May 03 08:11:00 CEST 2026",
      "times": {
        "calc_div2": "Mo17:39",
        "calc_div2_dt": "2026-05-04 17:39",
        "calc_div3": "Mo09:59",
        "calc_div3_dt": "2026-05-04 09:59",
        "from_meldung": "Mo14:00",
        "from_meldung_dt": "2026-05-04 14:00",
        "from_meldung_alt": null,
        "from_meldung_alt_dt": null
      },
      "bemerkung": ""
    },
    {
      "is_target": false,
      "pos": 47,
      "takt": "89,0",
      "vorname": "Lutz",
      "nachname": "Jeske",
      "arrow": null,
      "richtung": null,
      "verguetung": false,
      "zeit": "Sun May 03 09:41:00 CEST 2026",
      "times": {
        "calc_div2": "Mo18:09",
        "calc_div2_dt": "2026-05-04 18:09",
        "calc_div3": "Mo10:19",
        "calc_div3_dt": "2026-05-04 10:19",
        "from_meldung": "Mo14:00",
        "from_meldung_dt": "2026-05-04 14:00",
        "from_meldung_alt": null,
        "from_meldung_alt_dt": null
      },
      "bemerkung": ""
    },
    {
      "is_target": false,
      "pos": 48,
      "takt": "90,0",
      "vorname": "Sebastian",
      "nachname": "Klein",
      "arrow": null,
      "richtung": null,
      "verguetung": false,
      "zeit": "Sun May 03 09:47:00 CEST 2026",
      "times": {
        "calc_div2": "Mo18:39",
        "calc_div2_dt": "2026-05-04 18:39",
        "calc_div3": "Mo10:39",
        "calc_div3_dt": "2026-05-04 10:39",
        "from_meldung": "Mo15:00",
        "from_meldung_dt": "2026-05-04 15:00",
        "from_meldung_alt": null,
        "from_meldung_alt_dt": null
      },
      "bemerkung": ""
    },
    {
      "is_target": false,
      "pos": 49,
      "takt": "91,0",
      "vorname": "Lutz",
      "nachname": "Wäntig",
      "arrow": "↓",
      "richtung": "↓",
      "verguetung": false,
      "zeit": "Sun May 03 10:19:00 CEST 2026",
      "times": {
        "calc_div2": "Mo19:09",
        "calc_div2_dt": "2026-05-04 19:09",
        "calc_div3": "Mo10:59",
        "calc_div3_dt": "2026-05-04 10:59",
        "from_meldung": "Mo15:00",
        "from_meldung_dt": "2026-05-04 15:00",
        "from_meldung_alt": null,
        "from_meldung_alt_dt": null
      },
      "bemerkung": ""
    },
    {
      "is_target": false,
      "pos": 50,
      "takt": "92,0",
      "vorname": "Thomas",
      "nachname": "Dietrich",
      "arrow": null,
      "richtung": null,
      "verguetung": false,
      "zeit": "Sun May 03 10:44:00 CEST 2026",
      "times": {
        "calc_div2": "Mo19:39",
        "calc_div2_dt": "2026-05-04 19:39",
        "calc_div3": "Mo11:19",
        "calc_div3_dt": "2026-05-04 11:19",
        "from_meldung": "Mo15:00",
        "from_meldung_dt": "2026-05-04 15:00",
        "from_meldung_alt": null,
        "from_meldung_alt_dt": null
      },
      "bemerkung": ""
    },
    {
      "is_target": false,
      "pos": 51,
      "takt": "93,0",
      "vorname": "Klaus",
      "nachname": "Eidenschink",
      "arrow": null,
      "richtung": null,
      "verguetung": false,
      "zeit": "Sun May 03 10:58:00 CEST 2026",
      "times": {
        "calc_div2": "Mo20:09",
        "calc_div2_dt": "2026-05-04 20:09",
        "calc_div3": "Mo11:39",
        "calc_div3_dt": "2026-05-04 11:39",
        "from_meldung": "Mo15:20",
        "from_meldung_dt": "2026-05-04 15:20",
        "from_meldung_alt": null,
        "from_meldung_alt_dt": null
      },
      "bemerkung": ""
    },
    {
      "is_target": false,
      "pos": 52,
      "takt": "94,0",
      "vorname": "Olaf",
      "nachname": "Sattler",
      "arrow": null,
      "richtung": null,
      "verguetung": false,
      "zeit": "Sun May 03 11:09:00 CEST 2026",
      "times": {
        "calc_div2": "Mo20:39",
        "calc_div2_dt": "2026-05-04 20:39",
        "calc_div3": "Mo11:59",
        "calc_div3_dt": "2026-05-04 11:59",
        "from_meldung": "Mo16:00",
        "from_meldung_dt": "2026-05-04 16:00",
        "from_meldung_alt": null,
        "from_meldung_alt_dt": null
      },
      "bemerkung": ""
    },
    {
      "is_target": false,
      "pos": 53,
      "takt": "95,0",
      "vorname": "Ulrich",
      "nachname": "Diekmann",
      "arrow": null,
      "richtung": null,
      "verguetung": false,
      "zeit": "Sun May 03 11:13:00 CEST 2026",
      "times": {
        "calc_div2": "Mo21:09",
        "calc_div2_dt": "2026-05-04 21:09",
        "calc_div3": "Mo12:19",
        "calc_div3_dt": "2026-05-04 12:19",
        "from_meldung": "Mo17:00",
        "from_meldung_dt": "2026-05-04 17:00",
        "from_meldung_alt": null,
        "from_meldung_alt_dt": null
      },
      "bemerkung": ""
    },
    {
      "is_target": false,
      "pos": 54,
      "takt": "96,0",
      "vorname": "Caspar-Maria",
      "nachname": "Krüger",
      "arrow": "↑$$",
      "richtung": "↑",
      "verguetung": true,
      "zeit": "Sun May 03 12:30:00 CEST 2026",
      "times": {
        "calc_div2": "Mo21:39",
        "calc_div2_dt": "2026-05-04 21:39",
        "calc_div3": "Mo12:39",
        "calc_div3_dt": "2026-05-04 12:39",
        "from_meldung": "Mo17:00",
        "from_meldung_dt": "2026-05-04 17:00",
        "from_meldung_alt": null,
        "from_meldung_alt_dt": null
      },
      "bemerkung": ""
    },
    {
      "is_target": false,
      "pos": 55,
      "takt": "97,0",
      "vorname": "Erskine",
      "nachname": "Schuh",
      "arrow": null,
      "richtung": null,
      "verguetung": false,
      "zeit": "Sun May 03 13:20:00 CEST 2026",
      "times": {
        "calc_div2": "Mo22:09",
        "calc_div2_dt": "2026-05-04 22:09",
        "calc_div3": "Mo12:59",
        "calc_div3_dt": "2026-05-04 12:59",
        "from_meldung": "Mo18:00",
        "from_meldung_dt": "2026-05-04 18:00",
        "from_meldung_alt": null,
        "from_meldung_alt_dt": null
      },
      "bemerkung": ""
    },
    {
      "is_target": false,
      "pos": 56,
      "takt": "98,0",
      "vorname": "Alexander",
      "nachname": "Engel",
      "arrow": "↓$$",
      "richtung": "↓",
      "verguetung": true,
      "zeit": "Sun May 03 13:36:00 CEST 2026",
      "times": {
        "calc_div2": "Mo22:39",
        "calc_div2_dt": "2026-05-04 22:39",
        "calc_div3": "Mo13:19",
        "calc_div3_dt": "2026-05-04 13:19",
        "from_meldung": "Mo18:00",
        "from_meldung_dt": "2026-05-04 18:00",
        "from_meldung_alt": null,
        "from_meldung_alt_dt": null
      },
      "bemerkung": ""
    },
    {
      "is_target": false,
      "pos": 57,
      "takt": "99,0",
      "vorname": "Eike",
      "nachname": "Matysik",
      "arrow": null,
      "richtung": null,
      "verguetung": false,
      "zeit": "Sun May 03 13:58:00 CEST 2026",
      "times": {
        "calc_div2": "Mo23:09",
        "calc_div2_dt": "2026-05-04 23:09",
        "calc_div3": "Mo13:39",
        "calc_div3_dt": "2026-05-04 13:39",
        "from_meldung": null,
        "from_meldung_dt": null,
        "from_meldung_alt": null,
        "from_meldung_alt_dt": null
      },
      "bemerkung": ""
    },
    {
      "is_target": false,
      "pos": 58,
      "takt": "100,0",
      "vorname": "Henning",
      "nachname": "Blome",
      "arrow": "↓",
      "richtung": "↓",
      "verguetung": false,
      "zeit": "Sun May 03 15:18:00 CEST 2026",
      "times": {
        "calc_div2": "Mo23:39",
        "calc_div2_dt": "2026-05-04 23:39",
        "calc_div3": "Mo13:59",
        "calc_div3_dt": "2026-05-04 13:59",
        "from_meldung": null,
        "from_meldung_dt": null,
        "from_meldung_alt": null,
        "from_meldung_alt_dt": null
      },
      "bemerkung": ""
    },
    {
      "is_target": false,
      "pos": 59,
      "takt": "1,0",
      "vorname": "Christoph",
      "nachname": "Malik",
      "arrow": "↑$$",
      "richtung": "↑",
      "verguetung": true,
      "zeit": "Sun May 03 15:19:00 CEST 2026",
      "times": {
        "calc_div2": "Di00:09",
        "calc_div2_dt": "2026-05-05 00:09",
        "calc_div3": "Mo14:19",
        "calc_div3_dt": "2026-05-04 14:19",
        "from_meldung": null,
        "from_meldung_dt": null,
        "from_meldung_alt": null,
        "from_meldung_alt_dt": null
      },
      "bemerkung": "max.10.Wache"
    },
    {
      "is_target": false,
      "pos": 60,
      "takt": "2,0",
      "vorname": "Sascha",
      "nachname": "Külzer",
      "arrow": null,
      "richtung": null,
      "verguetung": false,
      "zeit": "Sun May 03 15:27:00 CEST 2026",
      "times": {
        "calc_div2": "Di00:39",
        "calc_div2_dt": "2026-05-05 00:39",
        "calc_div3": "Mo14:39",
        "calc_div3_dt": "2026-05-04 14:39",
        "from_meldung": null,
        "from_meldung_dt": null,
        "from_meldung_alt": null,
        "from_meldung_alt_dt": null
      },
      "bemerkung": ""
    },
    {
      "is_target": false,
      "pos": 61,
      "takt": "3,0",
      "vorname": "Alexander",
      "nachname": "Hren",
      "arrow": null,
      "richtung": null,
      "verguetung": false,
      "zeit": "Sun May 03 16:24:00 CEST 2026",
      "times": {
        "calc_div2": "Di01:09",
        "calc_div2_dt": "2026-05-05 01:09",
        "calc_div3": "Mo14:59",
        "calc_div3_dt": "2026-05-04 14:59",
        "from_meldung": null,
        "from_meldung_dt": null,
        "from_meldung_alt": null,
        "from_meldung_alt_dt": null
      },
      "bemerkung": ""
    },
    {
      "is_target": false,
      "pos": 62,
      "takt": "4,0",
      "vorname": "Sören",
      "nachname": "Ehlers",
      "arrow": null,
      "richtung": null,
      "verguetung": false,
      "zeit": "Sun May 03 16:25:00 CEST 2026",
      "times": {
        "calc_div2": "Di01:39",
        "calc_div2_dt": "2026-05-05 01:39",
        "calc_div3": "Mo15:19",
        "calc_div3_dt": "2026-05-04 15:19",
        "from_meldung": null,
        "from_meldung_dt": null,
        "from_meldung_alt": null,
        "from_meldung_alt_dt": null
      },
      "bemerkung": ""
    },
    {
      "is_target": false,
      "pos": 63,
      "takt": "5,0",
      "vorname": "Stefan",
      "nachname": "Domeier",
      "arrow": null,
      "richtung": null,
      "verguetung": false,
      "zeit": "Sun May 03 16:44:00 CEST 2026",
      "times": {
        "calc_div2": "Di02:09",
        "calc_div2_dt": "2026-05-05 02:09",
        "calc_div3": "Mo15:39",
        "calc_div3_dt": "2026-05-04 15:39",
        "from_meldung": null,
        "from_meldung_dt": null,
        "from_meldung_alt": null,
        "from_meldung_alt_dt": null
      },
      "bemerkung": ""
    },
    {
      "is_target": false,
      "pos": 64,
      "takt": "6,0",
      "vorname": "Fred",
      "nachname": "Spiekermann",
      "arrow": null,
      "richtung": null,
      "verguetung": false,
      "zeit": "Sun May 03 17:47:00 CEST 2026",
      "times": {
        "calc_div2": "Di02:39",
        "calc_div2_dt": "2026-05-05 02:39",
        "calc_div3": "Mo15:59",
        "calc_div3_dt": "2026-05-04 15:59",
        "from_meldung": null,
        "from_meldung_dt": null,
        "from_meldung_alt": null,
        "from_meldung_alt_dt": null
      },
      "bemerkung": ""
    },
    {
      "is_target": false,
      "pos": 65,
      "takt": "7,0",
      "vorname": "Joachim",
      "nachname": "Munz",
      "arrow": "↓$$",
      "richtung": "↓",
      "verguetung": true,
      "zeit": "Sun May 03 18:13:00 CEST 2026",
      "times": {
        "calc_div2": "Di03:09",
        "calc_div2_dt": "2026-05-05 03:09",
        "calc_div3": "Mo16:19",
        "calc_div3_dt": "2026-05-04 16:19",
        "from_meldung": null,
        "from_meldung_dt": null,
        "from_meldung_alt": null,
        "from_meldung_alt_dt": null
      },
      "bemerkung": ""
    }
  ]
}